{
    "multipart": [
        {
            "apply": {
                "model": "foundation:block/balustrade/acacia_post"
            },
            "when": {
                "up": "true"
            }
        },
        {
            "apply": {
                "model": "foundation:block/balustrade/acacia_side2",
                "uvlock": true
            },
            "when": {
                "north": "low"
            }
        },
        {
            "apply": {
                "model": "foundation:block/balustrade/acacia_side",
                "uvlock": false,
                "y": 90
            },
            "when": {
                "east": "low"
            }
        },
        {
            "apply": {
                "model": "foundation:block/balustrade/acacia_side",
                "uvlock": false,
                "y": 180
            },
            "when": {
                "south": "low"
            }
        },
        {
            "apply": {
                "model": "foundation:block/balustrade/acacia_side",
                "uvlock": false,
                "y": 270
            },
            "when": {
                "west": "low"
            }
        },
        {
            "apply": {
                "model": "foundation:block/balustrade/acacia_side_tall",
                "uvlock": true
            },
            "when": {
                "north": "tall"
            }
        },
        {
            "apply": {
                "model": "foundation:block/balustrade/acacia_side_tall",
                "uvlock": false,
                "y": 90
            },
            "when": {
                "east": "tall"
            }
        },
        {
            "apply": {
                "model": "foundation:block/balustrade/acacia_side_tall",
                "uvlock": false,
                "y": 180
            },
            "when": {
                "south": "tall"
            }
        },
        {
            "apply": {
                "model": "foundation:block/balustrade/acacia_side_tall",
                "uvlock": false,
                "y": 270
            },
            "when": {
                "west": "tall"
            }
        }
    ]
}
